[
  {
    "id": "rTLjwB6zOxV9S",
    "title": "tank GIF",
    "type": "gif"
  },
  {
    "id": "dwDvT7XyKViUg",
    "title": "tank GIF",
    "type": "gif"
  },
  {
    "id": "QR7SyBe7tQfPq",
    "title": "War History GIF",
    "type": "gif"
  },
  {
    "id": "7OdHlSBrp9Hc261ipE",
    "title": "War Thunder Tank GIF",
    "type": "gif"
  },
  {
    "id": "aAxi9vh9QWaQ1aIYP9",
    "title": "Sexy Pool Party GIF by brazz.inc",
    "type": "gif"
  },
  {
    "id": "2a5IGQ1n1Ap1e",
    "title": "tank GIF",
    "type": "gif"
  },
  {
    "id": "AQRMyiauVH2S2YH2rg",
    "title": "Cabletloth tank helldivers illuminate automaton GIF",
    "type": "gif"
  },
  {
    "id": "C3yix2SZvRBu0",
    "title": "tank satisfying GIF",
    "type": "gif"
  },
  {
    "id": "AgaXMCnoSbNHa",
    "title": "tank GIF",
    "type": "gif"
  },
  {
    "id": "OpLgwrJMcAstuiyMEn",
    "title": "Marching War Thunder GIF",
    "type": "gif"
  },
  {
    "id": "KcxTf64hiTXjO",
    "title": "cat tank GIF",
    "type": "gif"
  },
  {
    "id": "69xuyCP5TvuIUiBoUC",
    "title": "tank blastlands GIF by Strange Quest",
    "type": "gif"
  },
  {
    "id": "b41XDCqGmZnb1Yvn51",
    "title": "War Thunder Tank GIF",
    "type": "gif"
  },
  {
    "id": "cAWD7crk4NvmU",
    "title": "tank iii GIF",
    "type": "gif"
  },
  {
    "id": "gVeHZmgpGWAcltpDO6",
    "title": "Tank Refuel GIF by Aral AG",
    "type": "gif"
  },
  {
    "id": "Z0oPSbDzp2Mg0",
    "title": "tank GIF",
    "type": "gif"
  },
  {
    "id": "UueBlKWpahUfsDpE1P",
    "title": "Drivetanks boom tank cruising range GIF",
    "type": "gif"
  },
  {
    "id": "JGunlb6LbQlz2",
    "title": "water tank GIF",
    "type": "gif"
  },
  {
    "id": "A7IntvuVbWTCiu9Awr",
    "title": "War Thunder Thank You GIF",
    "type": "gif"
  },
  {
    "id": "dKTXIH76rYfD2",
    "title": "tank wtf GIF",
    "type": "gif"
  },
  {
    "id": "55bEBEYzAT2jS",
    "title": "house fails GIF",
    "type": "gif"
  },
  {
    "id": "G6tI6KL5o9lNWEcYKG",
    "title": "War Thunder Tank GIF",
    "type": "gif"
  },
  {
    "id": "zSdj03ihqN0ii4beFS",
    "title": "War Thunder Hello GIF",
    "type": "gif"
  },
  {
    "id": "OBhmTCuOXMAx2",
    "title": "Video gif. A small dog skitters its feet beneath a tank costume as its head pokes out and someone holds onto its leash.",
    "type": "gif"
  },
  {
    "id": "i2eABfJsyCVBFKnR6X",
    "title": "Frog Wow GIF by Turbo Toad",
    "type": "gif"
  },
  {
    "id": "3BZXY2mYHLuTOwV0RI",
    "title": "War Thunder Tank GIF",
    "type": "gif"
  },
  {
    "id": "15L4GgZxncHh6",
    "title": "Russia Crossing GIF",
    "type": "gif"
  },
  {
    "id": "YAPEBEopf39wGS3KZ0",
    "title": "Germany Tiger GIF",
    "type": "gif"
  },
  {
    "id": "WhCcrZiIzDjAAVj4Ii",
    "title": "War Thunder Tank GIF",
    "type": "gif"
  },
  {
    "id": "DwOH6d4a7mFZHHluKf",
    "title": "Magic Mar GIF",
    "type": "gif"
  },
  {
    "id": "Vhp3zge2fAASlWA8nN",
    "title": "Jump Jumping GIF by WorldofTanks",
    "type": "gif"
  },
  {
    "id": "HxMQUdnZHY5xDnHH8x",
    "title": "War Thunder Tank GIF",
    "type": "gif"
  },
  {
    "id": "fayFcp7dEEhG7Tma6i",
    "title": "Happy Fish Tank GIF by AquariumMe",
    "type": "gif"
  },
  {
    "id": "Vrl2vLUgMa0mhmzDpu",
    "title": "Wot War Thunder GIF",
    "type": "gif"
  },
  {
    "id": "JIS3HjZexQJsk",
    "title": "Cat Tank GIF",
    "type": "gif"
  },
  {
    "id": "l4FGD5KYukbHukdG0",
    "title": "excited hugh jackman GIF by ScreenJunkies",
    "type": "gif"
  },
  {
    "id": "KulZNyMraUAjx7pHsv",
    "title": "Vintage Fail GIF by US National Archives",
    "type": "gif"
  },
  {
    "id": "poZnXsKLvTVGo",
    "title": "Please Disperse Naked Gun GIF",
    "type": "gif"
  },
  {
    "id": "RlsNraZFFs6pa",
    "title": "ice tank GIF",
    "type": "gif"
  },
  {
    "id": "fVdIUJBqsbwpi3k8ZV",
    "title": "War Thunder Tank GIF",
    "type": "gif"
  },
  {
    "id": "ZEXPfnfSbYixzrmYLe",
    "title": "Wot T-34 GIF by WorldofTanks",
    "type": "gif"
  },
  {
    "id": "IwnwCHUAvxCHyD9F8M",
    "title": "prairiestormchasers tank stormchasing psc101 stormchasers GIF",
    "type": "gif"
  },
  {
    "id": "fKwBQnWqAJGFdRGPDp",
    "title": "Chill Streamer GIF",
    "type": "gif"
  },
  {
    "id": "qVsgrG192eraHgSkVp",
    "title": "War Tank GIF",
    "type": "gif"
  },
  {
    "id": "TMoUuph3woOcxk4Mil",
    "title": "Russian Dance GIF",
    "type": "gif"
  },
  {
    "id": "vCkXebTE3BtKw",
    "title": "pet hd GIF",
    "type": "gif"
  },
  {
    "id": "aQJQbxZ27QE3a4MEUR",
    "title": "Gervonta Davis Knockout GIF by SHOWTIME Sports",
    "type": "gif"
  },
  {
    "id": "NLXXDb2llw74Y",
    "title": "tank GIF",
    "type": "gif"
  },
  {
    "id": "T8xjpCSoyVqbWot0W4",
    "title": "War Thunder Tank GIF",
    "type": "gif"
  },
  {
    "id": "WMMQF9iK5BX2M",
    "title": "tank help GIF",
    "type": "gif"
  },
  {
    "id": "CPYzUeCfdclaoIMktG",
    "title": "Warrior Tank GIF",
    "type": "gif"
  },
  {
    "id": "EywssylBnDwqkDeaa3",
    "title": "Surfs Up Penguin GIF",
    "type": "gif"
  },
  {
    "id": "P8XNUbh3Wuwa4",
    "title": "tank crossing GIF",
    "type": "gif"
  },
  {
    "id": "5KTnNl34jE4Hp1c9nC",
    "title": "War Tank GIF",
    "type": "gif"
  },
  {
    "id": "lzHLywvMtvKYxBCPdn",
    "title": "Tank Mistake GIF by copochan",
    "type": "gif"
  },
  {
    "id": "1RLMlsZVw8dpkNWNEl",
    "title": "War Thunder Tank GIF",
    "type": "gif"
  },
  {
    "id": "6HsWsUPLmW4VmrFU4R",
    "title": "Girls Und Panzer Computer GIF",
    "type": "gif"
  },
  {
    "id": "3WWe87vLyvWtAIKflI",
    "title": "Cat Tank GIF by MEOW",
    "type": "gif"
  },
  {
    "id": "zHsgizjyyyRSrOap0n",
    "title": "Us Army Fire GIF by California Army National Guard",
    "type": "gif"
  },
  {
    "id": "9resXBcrl4LOTRK9KE",
    "title": "I Have To Pee Running Water GIF",
    "type": "gif"
  },
  {
    "id": "Hm2IQDcEWi8yDVW5bf",
    "title": "My Little Pony Tank GIF",
    "type": "gif"
  },
  {
    "id": "GmxuWtj7hHyCI",
    "title": "sexy long hair GIF",
    "type": "gif"
  },
  {
    "id": "E1IfgpJ3hW6lwFATy6",
    "title": "Tank GIF by SecondFront",
    "type": "gif"
  },
  {
    "id": "12sqJL27rYuJ4A",
    "title": "tank sherman GIF",
    "type": "gif"
  },
  {
    "id": "pieqpHOdbAbkJRUmR8",
    "title": "War Thunder Tank GIF",
    "type": "gif"
  },
  {
    "id": "CFw80mRHLRhuKikwkj",
    "title": "Fashion Love GIF by ArmyPink",
    "type": "gif"
  },
  {
    "id": "l41YgUJLRizi8WTRu",
    "title": "truck tank GIF",
    "type": "gif"
  },
  {
    "id": "nW7SLfh8NSXtjyBdHR",
    "title": "Cosplay Just Let It Happen GIF",
    "type": "gif"
  },
  {
    "id": "egR0LtIz4wKiQn1v3N",
    "title": "Run Over Winter GIF by SecondFront",
    "type": "gif"
  },
  {
    "id": "e0eeNNEI0mlMnUkxeb",
    "title": "Tank Wot GIF by WorldofTanks",
    "type": "gif"
  },
  {
    "id": "6liGJ9Lfhkug78GpR3",
    "title": "Rain I Deserve GIF by Tank",
    "type": "gif"
  },
  {
    "id": "FAvokKOipIntxNGSN0",
    "title": "War Thunder Tank GIF",
    "type": "gif"
  },
  {
    "id": "zHCaeFISO2hjG8Pcfo",
    "title": "Girls Und Panzer Dance GIF",
    "type": "gif"
  },
  {
    "id": "123xOhqpkS3N0Q",
    "title": "tank GIF",
    "type": "gif"
  },
  {
    "id": "ZOUq9OnoJ3O2lsGSqB",
    "title": "Sexy Pool Party GIF by brazz.inc",
    "type": "gif"
  },
  {
    "id": "moOLcEJyM3WVcBKWO1",
    "title": "Film Tank GIF",
    "type": "gif"
  },
  {
    "id": "jhNwTXcybGxV4X8SEK",
    "title": "Hold Up Tank GIF",
    "type": "gif"
  },
  {
    "id": "EW2iQO64JEAre2EfKX",
    "title": "Girls Und Panzer Girl GIF",
    "type": "gif"
  },
  {
    "id": "HnbUSlfHXTJuM",
    "title": "tank GIF",
    "type": "gif"
  },
  {
    "id": "y3ykOdHmsBXJP37FHi",
    "title": "War Thunder Elephant GIF",
    "type": "gif"
  },
  {
    "id": "iqs0u8CPTgsBpRv8Du",
    "title": "Tank Battle GIF by WorldofTanks",
    "type": "gif"
  },
  {
    "id": "eQhk6ESfUvVsI",
    "title": "tank drifting GIF",
    "type": "gif"
  },
  {
    "id": "2FQx0XQHVXaJq",
    "title": "plane dropping GIF",
    "type": "gif"
  },
  {
    "id": "8VIyAhzR74xR7NWF2U",
    "title": "Glitch Glow GIF by Xbox",
    "type": "gif"
  },
  {
    "id": "LqrJS3sBfT0N611ccV",
    "title": "America Texas GIF by Drivetanks",
    "type": "gif"
  },
  {
    "id": "XLqJj8TFbUMIhiIolZ",
    "title": "War Thunder Attack GIF",
    "type": "gif"
  },
  {
    "id": "xT5LMXZiK24YcGZqyA",
    "title": "happy bart simpson GIF",
    "type": "gif"
  },
  {
    "id": "GQM9u85FP37ZkgAZPH",
    "title": "War Thunder Meat GIF",
    "type": "gif"
  },
  {
    "id": "vg3QOf0RB595wIoOGa",
    "title": "Wot Soviet GIF by WorldofTanks",
    "type": "gif"
  },
  {
    "id": "RAgoumdefxkJhn9HhS",
    "title": "Turn Tank GIF by SecondFront",
    "type": "gif"
  },
  {
    "id": "dlh6CFa0O5ip1uwB7Q",
    "title": "germany vintage GIF by US National Archives",
    "type": "gif"
  },
  {
    "id": "puDse4Nn0XkTgLSyAj",
    "title": "Dragon Ball Punch GIF",
    "type": "gif"
  },
  {
    "id": "VHrFj2xNYodLrmMONj",
    "title": "Animation Sticker GIF by ezgi korba",
    "type": "gif"
  },
  {
    "id": "RJKKcgS2Jczi4NbBIL",
    "title": "Listen To Me Life GIF by U.S. Army",
    "type": "gif"
  },
  {
    "id": "JxyYDDwOH9Gqks20cw",
    "title": "Explosion Tank GIF by SecondFront",
    "type": "gif"
  },
  {
    "id": "YS50J6NM7YIAuGEppn",
    "title": "Red Star Win GIF by FK Crvena zvezda",
    "type": "gif"
  },
  {
    "id": "S9EjVU1SiB7ulKwRX7",
    "title": "Wot War GIF by WorldofTanks",
    "type": "gif"
  },
  {
    "id": "SztEzBWcJndqhdviQd",
    "title": "Tank Rb GIF by Blackground Records 2.0",
    "type": "gif"
  },
  {
    "id": "3oEjI1ASxWkXpLemeA",
    "title": "tennis GIF",
    "type": "gif"
  },
  {
    "id": "gomgkw1Al36gg",
    "title": "Tank GIF",
    "type": "gif"
  }
]