[
  {
    "id": "9u1J84ZtCSl9K",
    "title": "Digital art gif. Photo of a frog lying on its back on a lily pad, altered to look like it is breathing, hands across its belly, relaxing.",
    "type": "gif"
  },
  {
    "id": "9Fhef9QrfopsmcWvIA",
    "title": "Drawing Office GIF",
    "type": "gif"
  },
  {
    "id": "idYdfZ9xxVgVPNXjs0",
    "title": "Strawberry Fields Fruit GIF by Pog the Frog",
    "type": "gif"
  },
  {
    "id": "OZ6hlq4IlG3rBIUmoK",
    "title": "Drawing Doodle GIF",
    "type": "gif"
  },
  {
    "id": "XIuAEM0MY4zKa5pyz1",
    "title": "Help Me Frog GIF",
    "type": "gif"
  },
  {
    "id": "pf6xVNNXJjtXnSWxLY",
    "title": "Drawing Doodle GIF",
    "type": "gif"
  },
  {
    "id": "uEb7Wps1mWe5ffEkQv",
    "title": "Drawing Buffering GIF",
    "type": "gif"
  },
  {
    "id": "MRMiOr5ChK5B9SHHfk",
    "title": "Mad Frog GIF",
    "type": "gif"
  },
  {
    "id": "IH9NW501211oU3le7B",
    "title": "Bad News No GIF by ikas",
    "type": "gif"
  },
  {
    "id": "3ncFQubOLCrOTsogC3",
    "title": "Thinking Waiting GIF by Turbo Toad",
    "type": "gif"
  },
  {
    "id": "uzBlxdCuHIJzewPGs6",
    "title": "Drawing Doodle GIF",
    "type": "gif"
  },
  {
    "id": "RSrXlcUYEyTkkmiRY7",
    "title": "Spring Jumping GIF by TOAD 8",
    "type": "gif"
  },
  {
    "id": "IJw8FZ7WrMHoB2kidG",
    "title": "Illustration Drawing GIF",
    "type": "gif"
  },
  {
    "id": "DUNZaXquhdNyVSSnFK",
    "title": "Dance Drawing GIF",
    "type": "gif"
  },
  {
    "id": "HOsRixUmhVcZ2",
    "title": "Frog Michigan GIF",
    "type": "gif"
  },
  {
    "id": "G5PVSmVBLsqTX7wZe3",
    "title": "Look Looking GIF by Turbo Toad",
    "type": "gif"
  },
  {
    "id": "1EghTrigJJhq8",
    "title": "Text Street GIF",
    "type": "gif"
  },
  {
    "id": "XsWnDZT3Uqo6dsjozd",
    "title": "Angry Shake GIF by angy frog",
    "type": "gif"
  },
  {
    "id": "5tAYxVv38L7PcLIIEu",
    "title": "Bikini Beach Frog GIF by Soilbandit",
    "type": "gif"
  },
  {
    "id": "g27YZj5goSkSoVndJS",
    "title": "Frog Trend GIF",
    "type": "gif"
  },
  {
    "id": "k3j9oaRV4FAT3ksIG1",
    "title": "Tom And Jerry Kick GIF by Studio Voisier",
    "type": "gif"
  },
  {
    "id": "AhjupbaBuOG6EWAAVG",
    "title": "Drawing Doodle GIF",
    "type": "gif"
  },
  {
    "id": "c09yiyePL8zo25DqPf",
    "title": "Jump Jumping GIF",
    "type": "gif"
  },
  {
    "id": "HZj78aujhspwIsbwfS",
    "title": "Drawing Doodle GIF",
    "type": "gif"
  },
  {
    "id": "YtQyQahBsPX1FVMTWm",
    "title": "Frog Please GIF by Turbo Toad",
    "type": "gif"
  },
  {
    "id": "JdmClaSQupZ3ctw03d",
    "title": "Puerto Rico Pride GIF",
    "type": "gif"
  },
  {
    "id": "8ymzCkeb0e2hG",
    "title": "Top Hat Frog GIF",
    "type": "gif"
  },
  {
    "id": "O34OShDsHVtJkanlXv",
    "title": "Illustration Drawing GIF",
    "type": "gif"
  },
  {
    "id": "1XziHKvjKepnyXTPHN",
    "title": "Cat Dancing GIF",
    "type": "gif"
  },
  {
    "id": "NHSF7hRPZjTeIjwlRZ",
    "title": "Drawing Doodle GIF",
    "type": "gif"
  },
  {
    "id": "4EImve2YoI46Kjq0KY",
    "title": "Heart Love GIF",
    "type": "gif"
  },
  {
    "id": "bnpx3SyvpHa0na5cdA",
    "title": "Party Dj GIF",
    "type": "gif"
  },
  {
    "id": "oFZEgRSqvlcKvOa8IP",
    "title": "Dance Dnd GIF",
    "type": "gif"
  },
  {
    "id": "9pn7USiTqztexMFigj",
    "title": "Happy Dance GIF",
    "type": "gif"
  },
  {
    "id": "GUGmSEFhswM4zfi8Zs",
    "title": "Doodle Frog GIF",
    "type": "gif"
  },
  {
    "id": "x2B6cKOOsNF43x11kX",
    "title": "Bubble Tea Drawing GIF",
    "type": "gif"
  },
  {
    "id": "fsQWsFYeL7iASTiqlS",
    "title": "Sad Frog GIF by Turbo Toad",
    "type": "gif"
  },
  {
    "id": "ssjmqG89aQFNCiSCsi",
    "title": "6 7 Frog GIF by Turbo Toad",
    "type": "gif"
  },
  {
    "id": "G2WqcReAOd1DTKWWY4",
    "title": "Drawing Doodle GIF",
    "type": "gif"
  },
  {
    "id": "ecB4kOxI8fjVrnUg7X",
    "title": "Drawing Doodle GIF",
    "type": "gif"
  },
  {
    "id": "kddir6g4bt8q40elQ3",
    "title": "Frog Jumping GIF by PlayKids",
    "type": "gif"
  },
  {
    "id": "rGXuubWPEQrwnHQnzK",
    "title": "Fire Burn GIF",
    "type": "gif"
  },
  {
    "id": "y4o8sEisb3hRg1zP1Z",
    "title": "Bull Frog Hello GIF by Respective",
    "type": "gif"
  },
  {
    "id": "fEQHjNOrEB55mlKfRw",
    "title": "Drawing Doodle GIF",
    "type": "gif"
  },
  {
    "id": "K64TYvCquNClUtF0dK",
    "title": "Art Love GIF by Kibbi",
    "type": "gif"
  },
  {
    "id": "ZA79RlHVGi4OPReUxI",
    "title": "Car Driving GIF",
    "type": "gif"
  },
  {
    "id": "kKtfz1PBx4Dz8lvQLE",
    "title": "Bored Still Waiting GIF by Turbo Toad",
    "type": "gif"
  },
  {
    "id": "pWLSXjkAv1c1gwCB4E",
    "title": "Wave Hello GIF",
    "type": "gif"
  },
  {
    "id": "x9OCxR2VdgaKDSeJev",
    "title": "Angry Drawing GIF",
    "type": "gif"
  },
  {
    "id": "fqURUNHLrxrbQXM4Uk",
    "title": "Summer Illustration GIF",
    "type": "gif"
  },
  {
    "id": "flmQpYSiWitpzDMsdA",
    "title": "Illustration Drawing GIF",
    "type": "gif"
  },
  {
    "id": "TRpqsm72IXZ0nxoOMn",
    "title": "Illustration Drawing GIF",
    "type": "gif"
  },
  {
    "id": "sADVgAc7yAl8zEOObY",
    "title": "Drawing Doodle GIF",
    "type": "gif"
  },
  {
    "id": "zoJSKvaDehYbabvY17",
    "title": "I Did It Yes GIF by Turbo Toad",
    "type": "gif"
  },
  {
    "id": "7zfweQR6bUvu4JF4DW",
    "title": "I Love You Heart GIF by Ordinary Frends",
    "type": "gif"
  },
  {
    "id": "vxKHks41iavZ5unsAp",
    "title": "Health Club Gym GIF",
    "type": "gif"
  },
  {
    "id": "LamI12wy814kqkg3a6",
    "title": "Drawing Doodle GIF",
    "type": "gif"
  },
  {
    "id": "iVddRfGnwPd4TnZFpo",
    "title": "For You Love GIF",
    "type": "gif"
  },
  {
    "id": "iHelSt93ORqbFRnMYU",
    "title": "Friend Yes GIF by Froggy Friends",
    "type": "gif"
  },
  {
    "id": "JeN6aDuZBExGC1MPXX",
    "title": "On My Way Magic GIF",
    "type": "gif"
  },
  {
    "id": "gEC1vN1X0b8lkfq9Ku",
    "title": "Happy Party GIF",
    "type": "gif"
  },
  {
    "id": "34QNJ2bnKMtZD3DME8",
    "title": "Heart Drawing GIF",
    "type": "gif"
  },
  {
    "id": "HgwFlrFEsrqYNc3g5s",
    "title": "Drawing Doodle GIF",
    "type": "gif"
  },
  {
    "id": "PD7LvnIOrPZ0HezXzd",
    "title": "Illustration Drawing GIF",
    "type": "gif"
  },
  {
    "id": "6AsSlsPK0cuGqTiqWR",
    "title": "Bored Drawing GIF",
    "type": "gif"
  },
  {
    "id": "5xqyWhU3zZ0qZ6C6di",
    "title": "Sad Cry GIF",
    "type": "gif"
  },
  {
    "id": "w7p6htogcWX2FgIGpT",
    "title": "Frog Wednesday GIF by Ordinary Frends",
    "type": "gif"
  },
  {
    "id": "o3gx8LRkN4KHjilckw",
    "title": "Drawing Singing GIF",
    "type": "gif"
  },
  {
    "id": "5adwhTVSnS9SF9JplA",
    "title": "Drawing Doodle GIF",
    "type": "gif"
  },
  {
    "id": "c5aKzIpCduvJGdHwiG",
    "title": "Drawing Fly GIF",
    "type": "gif"
  },
  {
    "id": "gUMDcj4VsPr5fH8XIN",
    "title": "Angry Drawing GIF",
    "type": "gif"
  },
  {
    "id": "3StbjUZsxNFq8sIqvn",
    "title": "Drawing Doodle GIF",
    "type": "gif"
  },
  {
    "id": "Ty5qfkgold9OwORsK3",
    "title": "Drawing Doodle GIF",
    "type": "gif"
  },
  {
    "id": "c3uVflSV5pQvggyiNM",
    "title": "Drawing Disappear GIF",
    "type": "gif"
  },
  {
    "id": "Er2t4WJBcHAA0YHt9X",
    "title": "Doodle Fighting GIF",
    "type": "gif"
  },
  {
    "id": "NWDM3GKpoU4zFnCZCv",
    "title": "Drawing Doodle GIF",
    "type": "gif"
  },
  {
    "id": "Pa6h6P5dhin43OlwQ6",
    "title": "Cartoon gif. A green frog with a striped white and blue shirt and black spectacles jots something down on paper with a thick pencil. It stares at us before glancing back down at the paper. Text reads, \"Noted.\"",
    "type": "gif"
  },
  {
    "id": "eBrsV8a8N8TjW",
    "title": "New Orleans Love GIF",
    "type": "gif"
  },
  {
    "id": "GoiLJap1DuJebiehaH",
    "title": "Drawing Doodle GIF",
    "type": "gif"
  },
  {
    "id": "PXSjxQvgGnRCgKQKmu",
    "title": "Good Night Frog GIF by Ordinary Frends",
    "type": "gif"
  },
  {
    "id": "OBZhqKG33dRMWdtrjA",
    "title": "No Way Wow GIF by Turbo Toad",
    "type": "gif"
  },
  {
    "id": "CUYVTTUA7vasr0UOHd",
    "title": "Embarrassed Drawing GIF",
    "type": "gif"
  },
  {
    "id": "hwbfseoxdKgGu9GLwD",
    "title": "Drawing Doodle GIF",
    "type": "gif"
  },
  {
    "id": "g3ZDYhDXAh5satsICy",
    "title": "Frog Jump GIF",
    "type": "gif"
  },
  {
    "id": "KCe9K3t7lNs58UvobV",
    "title": "The_Frog_Mage magic fantasy frog wizard GIF",
    "type": "gif"
  },
  {
    "id": "d9DSJUNyEHUwsnvFC2",
    "title": "Happy Dance GIF",
    "type": "gif"
  },
  {
    "id": "yN3cD1p6bfTiCHRMLo",
    "title": "Illustration Drawing GIF",
    "type": "gif"
  },
  {
    "id": "hU7Tay5515RD2uYEBR",
    "title": "Drawing Doodle GIF",
    "type": "gif"
  },
  {
    "id": "wzMwBUSZaD8LlXwojP",
    "title": "Drawing Doodle GIF",
    "type": "gif"
  },
  {
    "id": "HyR6KjvVUV8bgzpARq",
    "title": "Motivation 加油 GIF",
    "type": "gif"
  },
  {
    "id": "Ugk7TQxDBplkF6vuQB",
    "title": "Sexy How You Doin GIF by Froggy Friends",
    "type": "gif"
  },
  {
    "id": "mef3aQeaDaAWYYsJr4",
    "title": "Drawing Doodle GIF",
    "type": "gif"
  },
  {
    "id": "tzmHeM1PaZaAyj0B1v",
    "title": "Gym Health GIF",
    "type": "gif"
  },
  {
    "id": "So5uZXO5jD2z7bA6b9",
    "title": "Frog Follow GIF",
    "type": "gif"
  },
  {
    "id": "l3iWm3PkHQtlBT3PEB",
    "title": "Illustration Drawing GIF",
    "type": "gif"
  },
  {
    "id": "cKAk5Jkeu5ONUpDQTV",
    "title": "Drawing Doodle GIF",
    "type": "gif"
  },
  {
    "id": "MxUDoGG7IJg1qWpQay",
    "title": "Kids Show Fly GIF by Treehouse Direct",
    "type": "gif"
  },
  {
    "id": "uM59qY3mpQJgOUDqQq",
    "title": "Drawing Goodbye GIF",
    "type": "gif"
  },
  {
    "id": "jZ2tdc7Jb24HUTScyw",
    "title": "Illustration Yes GIF",
    "type": "gif"
  },
  {
    "id": "ZUpYQDj3wHP6nlmLk6",
    "title": "Sad Drawing GIF",
    "type": "gif"
  }
]