[
  {
    "id": "OcwgZleO43Shy",
    "title": "Hold Up Baby GIF",
    "type": "gif"
  },
  {
    "id": "dV9O9k4Gt0NNkYkFPY",
    "title": "New Year Christmas GIF",
    "type": "gif"
  },
  {
    "id": "WtP7i8YX6E6Un7vpSM",
    "title": "Its A Boy Baby GIF by Foreskin Revolution",
    "type": "gif"
  },
  {
    "id": "VGuT6MILRVOnlLPFB5",
    "title": "Baby Boy GIF by FirstCry Parenting",
    "type": "gif"
  },
  {
    "id": "ukDW5WMF8RdkBOZMPw",
    "title": "Hallmark Ecards Baby GIF by Hallmark Gold Crown",
    "type": "gif"
  },
  {
    "id": "MABmcTItAXh7clerME",
    "title": "Baby Boy GIF by GreetPool",
    "type": "gif"
  },
  {
    "id": "m1am76VwLHNe6kOoYM",
    "title": "Happy Birthday Thank You GIF",
    "type": "gif"
  },
  {
    "id": "1091EolPQvocbS",
    "title": "boy GIF",
    "type": "gif"
  },
  {
    "id": "tflgRMLhDRzTkgL3ug",
    "title": "Baby Boy GIF by GreetPool",
    "type": "gif"
  },
  {
    "id": "OlvD9uWzVAO3ezZ5cn",
    "title": "New Baby GIF by MyPostcard",
    "type": "gif"
  },
  {
    "id": "yLD5PKYq7tsQZPZXpn",
    "title": "Celebrate Happy New Year GIF by Lucas and Friends by RV AppStudios",
    "type": "gif"
  },
  {
    "id": "PV2Kr7QS9rI8h2r6e0",
    "title": "Baby Boy Design GIF by Enchanted Studios",
    "type": "gif"
  },
  {
    "id": "WUs7JVwQL5zv5ccDgK",
    "title": "Baby Blues GIF by numa",
    "type": "gif"
  },
  {
    "id": "S5L0nNAM5JqwZOkIby",
    "title": "Pink Baby GIF by tutticuties",
    "type": "gif"
  },
  {
    "id": "K1OQRfUGlqLuzlzCYG",
    "title": "Baby Boy GIF by GreetPool",
    "type": "gif"
  },
  {
    "id": "WpOrKefhzgi5xrGw6A",
    "title": "My Princess GIF by FirstCry Parenting",
    "type": "gif"
  },
  {
    "id": "ZEU77DHt8k8azxfpxz",
    "title": "Daddys Girl Mom GIF by FirstCry Parenting",
    "type": "gif"
  },
  {
    "id": "vygSUXd8Q0OcOCE2n5",
    "title": "sleeplessparent baby girl baby names sleeplessparent baby girl announcement GIF",
    "type": "gif"
  },
  {
    "id": "l2YWxPbinlJYX5zMc",
    "title": "Mia Farrow Horror GIF by filmeditor",
    "type": "gif"
  },
  {
    "id": "21TLGIdROJLT2ERkmk",
    "title": "Baby Smile GIF by My Babblings",
    "type": "gif"
  },
  {
    "id": "lOUKO0Qmkomu6CGQjk",
    "title": "Baby Bday GIF by Nlb Vita",
    "type": "gif"
  },
  {
    "id": "2UKvpvCsXLTDlrvUM4",
    "title": "Customize Greeting Cards GIF by Greetings Island",
    "type": "gif"
  },
  {
    "id": "xT3i14Ddnbl75cEN4A",
    "title": "Cartoon gif. A baby hello kitty has her eyes closed as she sucks on a bottle in a bassinet. She wears a pink onesie and bonnet.",
    "type": "gif"
  },
  {
    "id": "nfzReVH7vxjJJGGTA9",
    "title": "Baby Boy GIF by GreetPool",
    "type": "gif"
  },
  {
    "id": "20zNepTj5Y1yIleraH",
    "title": "New Born Baby GIF by Hollyoaks",
    "type": "gif"
  },
  {
    "id": "cvHbna0lFYA7dGc3FX",
    "title": "Baby Boy Congrats GIF by GreetPool",
    "type": "gif"
  },
  {
    "id": "g5J6pilmOCoSL1nRRk",
    "title": "Baby Boy Animation GIF by Marianna",
    "type": "gif"
  },
  {
    "id": "NspG4nRIcgUO35f40p",
    "title": "Happy Birthday Success GIF by Enchanted Studios",
    "type": "gif"
  },
  {
    "id": "h8siZ3Uih5voMVpi3v",
    "title": "Baby Boy Hello GIF by Avery Products",
    "type": "gif"
  },
  {
    "id": "3HEMS9JYOp3XOaNb4Z",
    "title": "schitts creek crying GIF by CBC",
    "type": "gif"
  },
  {
    "id": "CT9lWeW2z6f169jPld",
    "title": "Baby Boy Congrats GIF by GreetPool",
    "type": "gif"
  },
  {
    "id": "IOozDaoQTA6gU",
    "title": "baby congratulations GIF",
    "type": "gif"
  },
  {
    "id": "13oWrv5RvpUIs77KlF",
    "title": "Baby Boy GIF by GreetPool",
    "type": "gif"
  },
  {
    "id": "P1Pa2OSgpJkfAtT5Qj",
    "title": "Baby Boy Congrats GIF by GreetPool",
    "type": "gif"
  },
  {
    "id": "KZwygcmhXonO5NoWj7",
    "title": "Tired Baby Blues GIF by numa",
    "type": "gif"
  },
  {
    "id": "rO4XaAF3AjgBdpERs0",
    "title": "Baby Boy GIF by GreetPool",
    "type": "gif"
  },
  {
    "id": "j2jqKZLkijcFTr9Wsv",
    "title": "Episode 2 Rachel GIF by Friends",
    "type": "gif"
  },
  {
    "id": "gRZjzexJSATcellUnQ",
    "title": "Donald Trump GIF by PBS NewsHour",
    "type": "gif"
  },
  {
    "id": "cbyTVD2bpVr9N2fbtO",
    "title": "New York Crying GIF",
    "type": "gif"
  },
  {
    "id": "bNcTXg4UgeydYWoBC9",
    "title": "Swinging New Baby GIF by Adventist Health",
    "type": "gif"
  },
  {
    "id": "tzj4fYkiwuea4DU5qP",
    "title": "Cat Baby GIF",
    "type": "gif"
  },
  {
    "id": "TlZNu5MnvMhpDOabcq",
    "title": "Baby Boy Congrats GIF by GreetPool",
    "type": "gif"
  },
  {
    "id": "879RsXB8GvEuY95LNl",
    "title": "Happy Birthday Success GIF by Enchanted Studios",
    "type": "gif"
  },
  {
    "id": "CX2pn94zLXZLrXf5kx",
    "title": "Wolf Cub Yes GIF",
    "type": "gif"
  },
  {
    "id": "DhJ8gLXgq60HOGg0lr",
    "title": "New York Art GIF",
    "type": "gif"
  },
  {
    "id": "Cc5j11fTWtFvzzC42U",
    "title": "sleeplessparent baby girl baby announcement baby names girl name GIF",
    "type": "gif"
  },
  {
    "id": "Pdemib8RWYn93Kvy7N",
    "title": "Expecting Teddy Bears GIF",
    "type": "gif"
  },
  {
    "id": "1hBSK3YNeN7kSv9uJf",
    "title": "Happy Girl GIF",
    "type": "gif"
  },
  {
    "id": "UVvyhnuz3kB4c0UZm5",
    "title": "Baby Boy GIF by FirstCry Parenting",
    "type": "gif"
  },
  {
    "id": "qblCh9lN38KTm4CIR7",
    "title": "Baby Boy Congrats GIF by GreetPool",
    "type": "gif"
  },
  {
    "id": "hITBi7O5K85261kISz",
    "title": "Fun Baby GIF by sendwishonline.com",
    "type": "gif"
  },
  {
    "id": "aI8pVDDlu8klaUKbSX",
    "title": "Baby Boy Congrats GIF by GreetPool",
    "type": "gif"
  },
  {
    "id": "0qIsURAqVuTLodiQyD",
    "title": "Go To Sleep No GIF by Chris Mann",
    "type": "gif"
  },
  {
    "id": "1Bdt0JOhuPJp3T6doK",
    "title": "New Baby GIF by Bilbareed",
    "type": "gif"
  },
  {
    "id": "VzAnGMAUJlXDIOUlGw",
    "title": "Chicken Grow GIF",
    "type": "gif"
  },
  {
    "id": "nMTomX5FoIPmw",
    "title": "baby boy congrats GIF",
    "type": "gif"
  },
  {
    "id": "Ef5auceg5gB9FNqYqP",
    "title": "Happy Birthday Success GIF by Enchanted Studios",
    "type": "gif"
  },
  {
    "id": "eMIIreVassxkOszkKE",
    "title": "Mad Jimmy Fallon GIF by Macmillan Kids",
    "type": "gif"
  },
  {
    "id": "QuD6pkPvlK0YkHoYkQ",
    "title": "Jimmy Fallon Baby GIF by Macmillan Kids",
    "type": "gif"
  },
  {
    "id": "hFuwjdPAXKO3qzPo7c",
    "title": "New Baby Love GIF by GreetPool",
    "type": "gif"
  },
  {
    "id": "glY5ZqA5Kzk2mpgl9V",
    "title": "Baby Boy GIF by GreetPool",
    "type": "gif"
  },
  {
    "id": "ixlG5NJJYDxNrhkvN9",
    "title": "Baby Boy GIF by Pudgy Penguins",
    "type": "gif"
  },
  {
    "id": "MSRzgBWVUaSD16XkZQ",
    "title": "New Baby GIF by evite",
    "type": "gif"
  },
  {
    "id": "0NjzyyQBi3vl0wieVi",
    "title": "New Baby Congratulations GIF by Cross Stitch Sanctuary",
    "type": "gif"
  },
  {
    "id": "jDTmyzEmh4XuIOpvM5",
    "title": "Meet The Fockers Baby GIF",
    "type": "gif"
  },
  {
    "id": "WTnA74FNjk01iZnu7N",
    "title": "Baby Boy GIF by GreetPool",
    "type": "gif"
  },
  {
    "id": "jVVItwah5JiD8dlhJT",
    "title": "Exploring New York GIF by Kimmy Ramone",
    "type": "gif"
  },
  {
    "id": "vr0W7IcHXRQb9IMUbZ",
    "title": "Nicole Kidman Its Mine GIF by HULU",
    "type": "gif"
  },
  {
    "id": "S2jpiFjgaMR1KhNVXk",
    "title": "Expecting New Baby GIF",
    "type": "gif"
  },
  {
    "id": "XfgpvcbgodGLk2qhnv",
    "title": "Baby Boy GIF by FirstCry Parenting",
    "type": "gif"
  },
  {
    "id": "9MJgsN6ug5jKZUeF3p",
    "title": "Good Night Baby GIF by Bilbareed",
    "type": "gif"
  },
  {
    "id": "kSvsoe4GQu4Wjiae1W",
    "title": "New Baby GIF by GreetPool",
    "type": "gif"
  },
  {
    "id": "aR6EppVWIipfpFlqaA",
    "title": "Baby Boy GIF by GreetPool",
    "type": "gif"
  },
  {
    "id": "syapuQTo2Xg1cAPYmC",
    "title": "May The Fourth Be With You Star Wars GIF",
    "type": "gif"
  },
  {
    "id": "jwCj8MGIUAq89fJnKR",
    "title": "Its A Boy Baby GIF by Pudgy Penguins",
    "type": "gif"
  },
  {
    "id": "NLIAkN0twDc63WPxBt",
    "title": "Baby Boy Congrats GIF by GreetPool",
    "type": "gif"
  },
  {
    "id": "DIB5QytnfYM424W4aX",
    "title": "New Baby GIF by GreetPool",
    "type": "gif"
  },
  {
    "id": "IWzAC2lMELuPQE1wWv",
    "title": "Eric Cartman Lol GIF by South Park",
    "type": "gif"
  },
  {
    "id": "02McoGFyL6cJSgfmlv",
    "title": "Baby Boy GIF by GreetPool",
    "type": "gif"
  },
  {
    "id": "StRKN6jyiRdxmfDQ85",
    "title": "Baby Boy Parents GIF by FirstCry Parenting",
    "type": "gif"
  },
  {
    "id": "s9hol3MKyhqHQmaYij",
    "title": "Baby Congratulations GIF by Floik",
    "type": "gif"
  },
  {
    "id": "lpHj9emjKnrtUGkgqP",
    "title": "New Baby Love GIF by sendwishonline.com",
    "type": "gif"
  },
  {
    "id": "1P9dIkUJfQ4u414oPe",
    "title": "Happy New Baby GIF by GreetPool",
    "type": "gif"
  },
  {
    "id": "SQFhkhWsQidPOy1Plw",
    "title": "New Baby GIF by GreetPool",
    "type": "gif"
  },
  {
    "id": "iZSylL1E1OI6Nz0ghI",
    "title": "Tired Baby Blues GIF by numa",
    "type": "gif"
  },
  {
    "id": "uxNjCb5GDqf9KnZokB",
    "title": "Boss Baby GIF by GreetPool",
    "type": "gif"
  },
  {
    "id": "ozH6a3gSOJGGGU8tGd",
    "title": "Misknursery love new baby rock GIF",
    "type": "gif"
  },
  {
    "id": "0YwOQ692UDIuOuuXLr",
    "title": "New Baby Girl GIF by GreetPool",
    "type": "gif"
  },
  {
    "id": "yq31Vhu1uwnsdKLVxM",
    "title": "Misknursery new baby home mom GIF",
    "type": "gif"
  },
  {
    "id": "uWXKHZqptWztK0uJ7n",
    "title": "Au Revoir Goodbye GIF by GreetPool",
    "type": "gif"
  },
  {
    "id": "JqKNQ1C1IsL1sdqIF9",
    "title": "Mothers Day Mother GIF by FirstCry Parenting",
    "type": "gif"
  },
  {
    "id": "tOICYjLmBoqQIsPdrJ",
    "title": "New Baby Pregnancy GIF by Channel Mum",
    "type": "gif"
  },
  {
    "id": "1z6oasYifdEyTOQIQM",
    "title": "Donald Trump GIF by PBS NewsHour",
    "type": "gif"
  },
  {
    "id": "i1J29fESXet3dLy9GJ",
    "title": "You Are Welcome GIF by Lucas and Friends by RV AppStudios",
    "type": "gif"
  },
  {
    "id": "KHQi3xJlbx2INz6QSm",
    "title": "Episode 2 Phoebe GIF by Friends",
    "type": "gif"
  },
  {
    "id": "p0dbzor8iuanohZBYD",
    "title": "Baby Boy Congrats GIF by GreetPool",
    "type": "gif"
  },
  {
    "id": "NlCsX4YGessSUW3Z87",
    "title": "TV gif. Milo Ventimiglia as Jack from This Is Us proudly holds two small babies: one in a pink blanket and one in a blue blanket.",
    "type": "gif"
  },
  {
    "id": "50Nk7i2Sw6wgg",
    "title": "R Kelly 90S GIF",
    "type": "gif"
  },
  {
    "id": "3d0ajCEEqfJXqPjLfw",
    "title": "live music 90s GIF by Live Nation",
    "type": "gif"
  },
  {
    "id": "RfpYtBzrH9wJWmirS0",
    "title": "Baby Boy GIF by FirstCry Parenting",
    "type": "gif"
  }
]